bbdtls/__init__.py
bbdtls/hello.py
bbdtls-0.1.0.dist-info/licenses/LICENSE
bbdtls-0.1.0.dist-info/METADATA
bbdtls-0.1.0.dist-info/WHEEL
bbdtls-0.1.0.dist-info/top_level.txt
bbdtls-0.1.0.dist-info/RECORD
