Metadata-Version: 2.4
Name: bbdtls
Version: 0.1.0
Summary: A set of daily used tools
Author-email: fbbmore <fbbyqsyea@gmail.com>
License: MIT
Project-URL: Homepage, https://github.com/fbbyqsyea/bbdtls
Project-URL: Repository, https://github.com/fbbyqsyea/bbdtls
Keywords: daily,tools
Classifier: Programming Language :: Python :: 3
Classifier: License :: OSI Approved :: MIT License
Classifier: Operating System :: OS Independent
Requires-Python: >=3.11
License-File: LICENSE
Provides-Extra: dev
Requires-Dist: pytest; extra == "dev"
Requires-Dist: pytest-cov; extra == "dev"
Provides-Extra: test
Requires-Dist: pytest; extra == "test"
Requires-Dist: pytest-cov; extra == "test"
Dynamic: license-file
